nonoLINE/__init__.py
nonoLINE/exception.py
nonoLINE/nono_line.py
nono_line-0.0.6.dist-info/LICENSE
nono_line-0.0.6.dist-info/METADATA
nono_line-0.0.6.dist-info/WHEEL
nono_line-0.0.6.dist-info/top_level.txt
nono_line-0.0.6.dist-info/RECORD
