Metadata-Version: 2.1
Name: nono-line
Version: 0.0.6
Summary: A simple notification helper to send messages to LINE Notify
Home-page: https://github.com/withsmilo/nonoLINE
Author: Sungjun, Kim
Author-email: smilolistener@gmail.com
License: MIT
Keywords: LINE,LINE Notify,notification,nonoLINE,nono-line
Platform: UNKNOWN
Classifier: Development Status :: 4 - Beta
Classifier: Intended Audience :: Developers
Classifier: Topic :: Software Development :: Libraries :: Python Modules
Classifier: License :: OSI Approved :: MIT License
Requires-Dist: requests
Requires-Dist: requests-futures
